test_cry/__init__.py
test_cry/some.py
test_cry-0.0.2.dist-info/METADATA
test_cry-0.0.2.dist-info/WHEEL
test_cry-0.0.2.dist-info/top_level.txt
test_cry-0.0.2.dist-info/RECORD
